Biclusters/__init__.py
Biclusters/bicluster_RNAseqDB_wrapper.py
CTD/CTD_wrapper.py
CTD/__init__.py
GeneStore/__init__.py
GeneStore/gene_store.py
GraphVisuals/__init__.py
GraphVisuals/graphviz_wrapper.py
MyGene/__init__.py
MyGene/mygene_client.py
OwlSim3/__init__.py
OwlSim3/owlsim_wrapper.py
Rhea/Rhea.py
Rhea/__init__.py
SimSearch/__init__.py
SimSearch/simsearch_client.py
UniProt/__init__.py
UniProt/uniprot_sparql_wrapper.py
biolink_api/__init__.py
biolink_api/biolink_api_client.py
mvp_module_library-0.1.0.dist-info/METADATA
mvp_module_library-0.1.0.dist-info/WHEEL
mvp_module_library-0.1.0.dist-info/top_level.txt
mvp_module_library-0.1.0.dist-info/RECORD
